logference/__init__.py
logference/main.py
logference/prompts.py
logference-2025.12.21182056.dist-info/METADATA
logference-2025.12.21182056.dist-info/WHEEL
logference-2025.12.21182056.dist-info/top_level.txt
logference-2025.12.21182056.dist-info/RECORD
