Metadata-Version: 2.4
Name: logference
Version: 2025.12.21182056
Summary: A new package would process user complaints or descriptions about logging systems, extracting structured insights such as common pain points, root causes, or improvement suggestions. It uses an LLM to
Author-email: logference <hi@eugene.plus>
License: MIT
Project-URL: Homepage, https://github.com/chigwell/logference
Requires-Python: >=3.9
Requires-Dist: langchain-llm7>=0.0.0
Requires-Dist: llmatch-messages>=0.0.0
Requires-Dist: langchain-core>=0.3.0
